Metadata-Version: 2.1
Name: pytest-custom-exit-code
Version: 0.2.1
Summary: Exit pytest test session with custom exit code in different scenarios
Home-page: https://github.com/yashtodi94/pytest-custom_exit_code
Author: Yash Todi
Author-email: yashtodi94@gmail.com
Maintainer: Yash Todi
Maintainer-email: yashtodi94@gmail.com
License: MIT
Platform: UNKNOWN
Classifier: Development Status :: 4 - Beta
Classifier: Framework :: Pytest
Classifier: Intended Audience :: Developers
Classifier: Topic :: Software Development :: Testing
Classifier: Programming Language :: Python
Classifier: Programming Language :: Python :: 3.4
Classifier: Programming Language :: Python :: 3.5
Classifier: Programming Language :: Python :: 3.6
Classifier: Programming Language :: Python :: 3.7
Classifier: Programming Language :: Python :: Implementation :: CPython
Classifier: Operating System :: OS Independent
Classifier: License :: OSI Approved :: MIT License
Requires-Python: >2.7, !=3.0.*, !=3.1.*, !=3.2.*, !=3.3.*
Requires-Dist: pytest (>=4.0.2)
